masterful/__init__.py
masterful/architecture.py
masterful/constants.py
masterful/data.py
masterful/enums.py
masterful/optimization.py
masterful/regularization.py
masterful/ssl.py
masterful/training.py
masterful/version.py
masterful/proto/__init__.py
masterful/proto/log_pb2.py
masterful/utils/__init__.py
masterful/utils/register.py
mful_dev-0.4.1.dev202204251650943961.dist-info/LICENSE
mful_dev-0.4.1.dev202204251650943961.dist-info/METADATA
mful_dev-0.4.1.dev202204251650943961.dist-info/WHEEL
mful_dev-0.4.1.dev202204251650943961.dist-info/top_level.txt
mful_dev-0.4.1.dev202204251650943961.dist-info/RECORD
