Metadata-Version: 2.1
Name: mful-dev
Version: 0.4.1.dev202204251650943961
Summary: Masterful AutoML Platform.
Home-page: http://masterfulai.com
Author: Masterful AI
Author-email: learn@masterfulai.com
License: Copyright 2022, Masterful AI, Inc.
Platform: UNKNOWN
Classifier: Programming Language :: Python :: 3
Classifier: Programming Language :: Python :: 3.6
Classifier: Programming Language :: Python :: 3.7
Classifier: Programming Language :: Python :: 3.8
Classifier: Programming Language :: Python :: 3.9
Classifier: Programming Language :: Python :: 3 :: Only
Classifier: Operating System :: OS Independent
Classifier: Intended Audience :: Developers
Classifier: Intended Audience :: Education
Classifier: Intended Audience :: Science/Research
Classifier: Topic :: Scientific/Engineering
Classifier: Topic :: Scientific/Engineering :: Mathematics
Classifier: Topic :: Scientific/Engineering :: Artificial Intelligence
Classifier: Topic :: Software Development
Classifier: Topic :: Software Development :: Libraries
Classifier: Topic :: Software Development :: Libraries :: Python Modules
Requires-Python: >=3.6
Requires-Dist: protobuf
Requires-Dist: pandas
Requires-Dist: plotly
Requires-Dist: inject
Requires-Dist: tensorflow-addons
Requires-Dist: psutil
Requires-Dist: packaging
Requires-Dist: typing-extensions
Requires-Dist: tqdm
Requires-Dist: memory-tempfile
Requires-Dist: requests
Requires-Dist: dataclasses
Requires-Dist: albumentations
Requires-Dist: pycocotools
Requires-Dist: mful-gui-dev
